manoj_server/__init__.py
manoj_server/manoj_server.py
manoj_server-1.0.3.dist-info/LICENSE
manoj_server-1.0.3.dist-info/METADATA
manoj_server-1.0.3.dist-info/WHEEL
manoj_server-1.0.3.dist-info/entry_points.txt
manoj_server-1.0.3.dist-info/top_level.txt
manoj_server-1.0.3.dist-info/RECORD
