Metadata-Version: 2.1
Name: manoj-server
Version: 1.0.3
Summary: This is personal server
Author: Manoj
Author-email: mmanoj20037@gmail.com
Classifier: Programming Language :: Python :: 3
Classifier: License :: OSI Approved :: MIT License
Classifier: Operating System :: OS Independent
License-File: LICENSE
